{
  "products": [
    {
      " id": 1,
      "name": "Tray 1",
      "image": "",
      "description": "",
      "categoryId": 5
    },
    {
      "id": 2,
      "name": "Chess Board 1",
      "image": "",
      "description": "",
      "categoryId": 2
    },
    {
      "id": 3,
      "name": "Bar 1",
      "image": "",
      "description": "",
      "categoryId": 4
    },
    {
      " id": 4,
      "name": "Table 1",
      "image": "",
      "description": "",
      "categoryId": 1
    },
    {
      "id": 5,
      "name": "Table 2",
      "image": "",
      "description": "",
      "categoryId": 1
    },
    {
      "id": 6,
      "name": "Table 3",
      "image": "",
      "description": "",
      "categoryId": 1
    },
    {
      "id": 7,
      "name": "Table 4",
      "image": "",
      "description": "",
      "categoryId": 1
    },
    {
      "id": 8,
      "name": "Table 5",
      "image": "",
      "description": "",
      "categoryId": 1
    },

    {
      "id": 9,
      "name": "Wall Clock 1",
      "image": "",
      "description": "",
      "categoryId": 3
    },
    {
      "id": 10,
      "name": "Wall Clock 2",
      "image": "",
      "description": "",
      "categoryId": 3
    },
    {
      "id": 11,
      "name": "Wall Clock 3",
      "image": "",
      "description": "",
      "categoryId": 3
    },
    {
      "id": 12,
      "name": "Wall Clock 4",
      "image": "",
      "description": "",
      "categoryId": 3
    },
    {
      "id": 13,
      "name": "Wall Clock 5",
      "image": "",
      "description": "",
      "categoryId": 3
    },
    {
      "id": 14,
      "name": "Wall Clock 6",
      "image": "",
      "description": "",
      "categoryId": 3
    },
    {
      "id": 15,
      "name": "Wall Clock 7",
      "image": "",
      "description": "",
      "categoryId": 3
    }
  ],

  "categories": [
    {
      "categoryId": 1,
      "name": "Table"
    },
    {
      "categoryId": 2,
      "name": "ChessBoard"
    },
    {
      "categoryId": 3,
      "name": "WallClock"
    },
    {
      "categoryId": 4,
      "name": "Bar"
    },
    {
      "categoryId": 5,
      "name": "Tray"
    }
  ]
}
